StaticTypedList/StaticTypedList.py
StaticTypedList/StaticTypedList_tests.py
StaticTypedList/StaticTypedList_versus_list.py
StaticTypedList-1.dist-info/LICENSE
StaticTypedList-1.dist-info/METADATA
StaticTypedList-1.dist-info/WHEEL
StaticTypedList-1.dist-info/entry_points.txt
StaticTypedList-1.dist-info/top_level.txt
StaticTypedList-1.dist-info/RECORD
