Metadata-Version: 2.1
Name: StaticTypedList
Version: 1
Summary: This package contains implementation of the library "StaticTypedList". StaticTypedList is a data type supporting a list of one type of element (and its subtypes) like Java List objects.
Home-page: https://github.com/DigitalCreativeApkDev/StaticTypedList
Author: DigitalCreativeApkDev
Author-email: digitalcreativeapkdev2022@gmail.com
License: MIT
Platform: UNKNOWN
Classifier: Programming Language :: Python :: 3
Classifier: Programming Language :: Python :: 3.7
